emeki/__init__.py
emeki/main.py
emeki/project_setup.py
emeki/testing.py
emeki/util.py
emeki/template/template.zip
emeki-0.1.9.dist-info/LICENSE
emeki-0.1.9.dist-info/METADATA
emeki-0.1.9.dist-info/WHEEL
emeki-0.1.9.dist-info/entry_points.txt
emeki-0.1.9.dist-info/top_level.txt
emeki-0.1.9.dist-info/RECORD
