Metadata-Version: 2.1
Name: emeki
Version: 0.1.9
Summary: Test
Home-page: https://github.com/chbauman/emeki
Author: Christian Baumann
Author-email: chris.python.notifyer@gmail.com
License: MIT
Platform: UNKNOWN
Classifier: Programming Language :: Python
Classifier: Programming Language :: Python :: 3.6
Classifier: Operating System :: OS Independent
Classifier: Topic :: Utilities
Requires-Python: >=3.6
